msteamsadaptivecardbuilder.py
msteamsadaptivecardbuilder-1.1.0.data/data/LICENSE.txt
msteamsadaptivecardbuilder-1.1.0.dist-info/LICENSE.txt
msteamsadaptivecardbuilder-1.1.0.dist-info/METADATA
msteamsadaptivecardbuilder-1.1.0.dist-info/WHEEL
msteamsadaptivecardbuilder-1.1.0.dist-info/top_level.txt
msteamsadaptivecardbuilder-1.1.0.dist-info/RECORD
