Metadata-Version: 2.1
Name: msteamsadaptivecardbuilder
Version: 1.1.0
Summary: Easily Build and Export Multilingual Adaptive Cards Through Python
Home-page: https://github.com/NandovdK/AdaptiveCardBuilder
Author: Nando van der Kant
Author-email: njvdkant@gmail.com
Classifier: Programming Language :: Python :: 3
Classifier: Programming Language :: Python :: 3.6
Classifier: Programming Language :: Python :: 3.7
Classifier: Programming Language :: Python :: 3.8
Classifier: Programming Language :: Python :: 3.9
Classifier: License :: OSI Approved :: MIT License
Classifier: Operating System :: OS Independent
Classifier: Development Status :: 1 - Planning
License-File: LICENSE.txt
Requires-Dist: aiohttp
Requires-Dist: requests
